{
    "": "https://www.castorama.ru/paint/ukryvnoj-material",
    "Краскидлявнутреннихработ": "https://www.castorama.ru/paint/interior-paint",
    "Краскидлянаружныхработ": "https://www.castorama.ru/paint/exterior-paint",
    "Колерыдлякраски": "https://www.castorama.ru/paint/colourants",
    "Средствадлязащитыдревесиныиминеральныхоснований": "https://www.castorama.ru/paint/wood-protection",
    "Декоративныештукатурки": "https://www.castorama.ru/paint/decorative-plaster",
    "Эмали": "https://www.castorama.ru/paint/enamels",
    "Аэрозольныекраскиилакивбаллончиках": "https://www.castorama.ru/paint/sprays",
    "Лаки": "https://www.castorama.ru/paint/varnishes",
    "Растворители": "https://www.castorama.ru/paint/dissolvers",
    "Клейиклейкиеленты": "https://www.castorama.ru/paint/adhesives-and-glues",
    "Малярныйинструментиукрывнойматериал": "https://www.castorama.ru/paint/ukryvnoj-material"
}